open_cli3/__init__.py
open_cli3/cli.py
open_cli3/completer.py
open_cli3/formatter.py
open_cli3/help.py
open_cli3/main.py
open_cli3/openapi_extension.py
open_cli3/parser.py
open_cli3-0.0.0.dist-info/AUTHORS
open_cli3-0.0.0.dist-info/LICENSE
open_cli3-0.0.0.dist-info/METADATA
open_cli3-0.0.0.dist-info/WHEEL
open_cli3-0.0.0.dist-info/entry_points.txt
open_cli3-0.0.0.dist-info/pbr.json
open_cli3-0.0.0.dist-info/top_level.txt
open_cli3-0.0.0.dist-info/RECORD
