Metadata-Version: 2.1
Name: open-cli3
Version: 0.0.0
Summary: Generate client based on OpenAPI Specification and wrap it in a command line interface
Home-page: https://github.com/privcloud-com/open-cli3
Author: Danny Tijerina
Author-email: danny@privcloud.com
License: MIT
Platform: UNKNOWN
Classifier: Environment :: Console
Classifier: Intended Audience :: Information Technology
Classifier: Intended Audience :: System Administrators
Classifier: Operating System :: POSIX :: Linux
Classifier: Programming Language :: Python
Classifier: Programming Language :: Python :: 3
Classifier: Programming Language :: Python :: 3.6
License-File: LICENSE
License-File: AUTHORS
Requires-Dist: certifi (==2021.5.30)
Requires-Dist: fire (==0.1.3)
Requires-Dist: openapi3 (==1.5.0)
Requires-Dist: prompt-toolkit (==1.0.15)
Requires-Dist: pyfiglet (==0.8.post1)
Requires-Dist: tabulate (==0.8.2)
Requires-Dist: wcwidth (==0.2.5)
Requires-Dist: six (==1.16.0) ; (python_version >= '2.7' and python_version not in '3.0, 3.1, 3.2, 3.3')
Requires-Dist: urllib3 (==1.26.6) ; (python_version >= '2.7' and python_version not in '3.0, 3.1, 3.2, 3.3, 3.4' and python_version < '4')
Requires-Dist: pyyaml (==5.4.1) ; (python_version >= '2.7' and python_version not in '3.0, 3.1, 3.2, 3.3, 3.4, 3.5')
Requires-Dist: requests (==2.26.0) ; (python_version >= '2.7' and python_version not in '3.0, 3.1, 3.2, 3.3, 3.4, 3.5')
Requires-Dist: charset-normalizer (==2.0.3) ; (python_version >= '3')
Requires-Dist: idna (==3.2) ; (python_version >= '3')
